i_bip_wallet/__init__.py
i_bip_wallet/_PrivateKey.py
i_bip_wallet/_PublicKey.py
i_bip_wallet/_Ripemd.py
i_bip_wallet/_Segwit.py
i_bip_wallet/_Utils.py
i_bip_wallet-1.0.0rc4.dist-info/WHEEL
i_bip_wallet-1.0.0rc4.dist-info/METADATA
i_bip_wallet-1.0.0rc4.dist-info/RECORD
