Metadata-Version: 2.1
Name: i-bip-wallet
Version: 1.0.0rc4
Summary: 
Author: DesKaOne
Author-email: DesKaOne@users.noreply.github.com
Requires-Python: >=3.8,<4.0
Classifier: Programming Language :: Python :: 3
Classifier: Programming Language :: Python :: 3.8
Classifier: Programming Language :: Python :: 3.9
Classifier: Programming Language :: Python :: 3.10
Classifier: Programming Language :: Python :: 3.11
Requires-Dist: ecdsa (>=0.18.0,<0.19.0)
Requires-Dist: pycryptodomex (>=3.20.0,<4.0.0)
